Metadata-Version: 2.1
Name: lazyllm-llamafactory
Version: 0.8.3
Summary: Easy-to-use LLM fine-tuning framework
Home-page: https://github.com/hiyouga/LLaMA-Factory
Author: hiyouga
Author-email: hiyouga@buaa.edu.cn
License: Apache 2.0 License
Keywords: LLaMA,BLOOM,Falcon,LLM,ChatGPT,transformer,pytorch,deep learning
Classifier: Development Status :: 4 - Beta
Classifier: Intended Audience :: Developers
Classifier: Intended Audience :: Education
Classifier: Intended Audience :: Science/Research
Classifier: License :: OSI Approved :: Apache Software License
Classifier: Operating System :: OS Independent
Classifier: Programming Language :: Python :: 3
Classifier: Programming Language :: Python :: 3.8
Classifier: Programming Language :: Python :: 3.9
Classifier: Programming Language :: Python :: 3.10
Classifier: Programming Language :: Python :: 3.11
Classifier: Topic :: Scientific/Engineering :: Artificial Intelligence
Requires-Python: >=3.8.0
License-File: LICENSE
Requires-Dist: transformers (>=4.41.2)
Requires-Dist: datasets (>=2.16.0)
Requires-Dist: accelerate (>=0.30.1)
Requires-Dist: peft (>=0.11.1)
Requires-Dist: trl (>=0.8.6)
Requires-Dist: gradio (>=4.0.0)
Requires-Dist: pandas (>=2.0.0)
Requires-Dist: scipy
Requires-Dist: einops
Requires-Dist: sentencepiece
Requires-Dist: tiktoken
Requires-Dist: protobuf
Requires-Dist: uvicorn
Requires-Dist: pydantic
Requires-Dist: fastapi
Requires-Dist: sse-starlette
Requires-Dist: matplotlib (>=3.7.0)
Requires-Dist: fire
Requires-Dist: packaging
Requires-Dist: pyyaml
Requires-Dist: numpy (<2.0.0)
Provides-Extra: aqlm
Requires-Dist: aqlm[gpu] (>=1.1.0) ; extra == 'aqlm'
Provides-Extra: awq
Requires-Dist: autoawq ; extra == 'awq'
Provides-Extra: badam
Requires-Dist: badam (>=1.2.1) ; extra == 'badam'
Provides-Extra: bitsandbytes
Requires-Dist: bitsandbytes (>=0.39.0) ; extra == 'bitsandbytes'
Provides-Extra: deepspeed
Requires-Dist: deepspeed (>=0.10.0) ; extra == 'deepspeed'
Provides-Extra: dev
Requires-Dist: ruff ; extra == 'dev'
Requires-Dist: pytest ; extra == 'dev'
Provides-Extra: eetq
Requires-Dist: eetq ; extra == 'eetq'
Provides-Extra: galore
Requires-Dist: galore-torch ; extra == 'galore'
Provides-Extra: gptq
Requires-Dist: optimum (>=1.17.0) ; extra == 'gptq'
Requires-Dist: auto-gptq (>=0.5.0) ; extra == 'gptq'
Provides-Extra: hqq
Requires-Dist: hqq ; extra == 'hqq'
Provides-Extra: metrics
Requires-Dist: nltk ; extra == 'metrics'
Requires-Dist: jieba ; extra == 'metrics'
Requires-Dist: rouge-chinese ; extra == 'metrics'
Provides-Extra: modelscope
Requires-Dist: modelscope ; extra == 'modelscope'
Provides-Extra: qwen
Requires-Dist: transformers-stream-generator ; extra == 'qwen'
Provides-Extra: torch
Requires-Dist: torch (>=1.13.1) ; extra == 'torch'
Provides-Extra: torch-npu
Requires-Dist: torch (==2.1.0) ; extra == 'torch-npu'
Requires-Dist: torch-npu (==2.1.0.post3) ; extra == 'torch-npu'
Requires-Dist: decorator ; extra == 'torch-npu'
Provides-Extra: vllm
Requires-Dist: vllm (>=0.4.3) ; extra == 'vllm'
